.VERSION
AUTHORS.rst
CONTRIBUTING.rst
HISTORY.rst
LICENSE
MANIFEST.in
Pipfile
Pipfile.lock
README.rst
USAGE.rst
dev-requirements.txt
requirements.txt
setup.cfg
setup.py
docs/Makefile
docs/authors.rst
docs/conf.py
docs/contributing.rst
docs/history.rst
docs/index.rst
docs/installation.rst
docs/readme.rst
docs/usage.rst
tests/test_wikiseriesasorkunlib.py
wikiseriesasorkunlib/.VERSION
wikiseriesasorkunlib/AUTHORS.rst
wikiseriesasorkunlib/CONTRIBUTING.rst
wikiseriesasorkunlib/HISTORY.rst
wikiseriesasorkunlib/LICENSE
wikiseriesasorkunlib/Pipfile
wikiseriesasorkunlib/Pipfile.lock
wikiseriesasorkunlib/README.rst
wikiseriesasorkunlib/USAGE.rst
wikiseriesasorkunlib/__init__.py
wikiseriesasorkunlib/_version.py
wikiseriesasorkunlib/dev-requirements.txt
wikiseriesasorkunlib/requirements.txt
wikiseriesasorkunlib/wikiseriesasorkunlib.py
wikiseriesasorkunlib/wikiseriesasorkunlibexceptions.py
wikiseriesasorkunlib.egg-info/PKG-INFO
wikiseriesasorkunlib.egg-info/SOURCES.txt
wikiseriesasorkunlib.egg-info/dependency_links.txt
wikiseriesasorkunlib.egg-info/not-zip-safe
wikiseriesasorkunlib.egg-info/requires.txt
wikiseriesasorkunlib.egg-info/top_level.txt