Metadata-Version: 2.1
Name: wikiseriesasorkunlib
Version: 0.1.0
Summary: This my project
Home-page: https://github.com/alisorkuncuk/wikiseriesasorkunlib
Author: Costas Tyfoxylos
Author-email: asork@gmail.com
License: MIT
Keywords: wikiseriesasorkunlib tv series
Classifier: Development Status :: 3 - Alpha
Classifier: Intended Audience :: Developers
Classifier: License :: OSI Approved :: MIT License
Classifier: Natural Language :: English
Classifier: Programming Language :: Python :: 3.9
License-File: LICENSE
License-File: AUTHORS.rst
